{
  "@context": {
    "@vocab": "https://schema.org/",
    "rcsg-fw": "https://platformcore.io/ontology/cg/"
  },
  "@type": "DataSet",
  "@id": "rcsg-fw:mapping-instances-v1.0.0",
  "metadata": {
    "name": "RCSG-FW Cross-Framework Governance Mapping Instances",
    "version": "2.0.0",
    "description": "Cross-framework mapping instances linking 22 NCSC Cyber Governance Code actions to 9 international standards, part of the merged RCSG-FW v2.0.0 ontology",
    "oaaVersion": "6.1.0",
    "dateCreated": "2026-02-16",
    "creator": "Azlan EA-AAA",
    "sourceDocument": "DSIT Cyber Governance Mapping (August 2025) \u2014 10-sheet XLSX",
    "totalMappings": 150,
    "frameworks": 9,
    "actions": 22,
    "dateModified": "2026-02-16"
  },
  "instances": [
    {
      "@id": "rcsg-fw:map-A1-CAF-001",
      "@type": "rcsg-fw:GovernanceActionMapping",
      "actionRef": "rcsg-fw:action-A1",
      "mappingId": "MAP-A1-CAF-001",
      "targetFramework": "NCSC CAF",
      "targetFrameworkVersion": "4.0",
      "targetControlId": "A3",
      "targetControlName": "Asset Management",
      "mappingStrength": "Partial",
      "mappingNotes": "Risk appetite determination aligns to CAF asset management identification"
    },
    {
      "@id": "rcsg-fw:map-A2-CAF-001",
      "@type": "rcsg-fw:GovernanceActionMapping",
      "actionRef": "rcsg-fw:action-A2",
      "mappingId": "MAP-A2-CAF-001",
      "targetFramework": "NCSC CAF",
      "targetFrameworkVersion": "4.0",
      "targetControlId": "A1",
      "targetControlName": "Governance",
      "mappingStrength": "Full",
      "mappingNotes": "Asset identification maps directly to CAF governance principle"
    },
    {
      "@id": "rcsg-fw:map-A3-CAF-001",
      "@type": "rcsg-fw:GovernanceActionMapping",
      "actionRef": "rcsg-fw:action-A3",
      "mappingId": "MAP-A3-CAF-001",
      "targetFramework": "NCSC CAF",
      "targetFrameworkVersion": "4.0",
      "targetControlId": "A2",
      "targetControlName": "Cyber Risk Management",
      "mappingStrength": "Full",
      "mappingNotes": "Risk assessment maps directly to CAF cyber risk management"
    },
    {
      "@id": "rcsg-fw:map-A4-CAF-001",
      "@type": "rcsg-fw:GovernanceActionMapping",
      "actionRef": "rcsg-fw:action-A4",
      "mappingId": "MAP-A4-CAF-001",
      "targetFramework": "NCSC CAF",
      "targetFrameworkVersion": "4.0",
      "targetControlId": "A4",
      "targetControlName": "Supply Chain",
      "mappingStrength": "Partial",
      "mappingNotes": "Threat landscape understanding aligns to CAF supply chain principle"
    },
    {
      "@id": "rcsg-fw:map-A5-CAF-001",
      "@type": "rcsg-fw:GovernanceActionMapping",
      "actionRef": "rcsg-fw:action-A5",
      "mappingId": "MAP-A5-CAF-001",
      "targetFramework": "NCSC CAF",
      "targetFrameworkVersion": "4.0",
      "targetControlId": "A2",
      "targetControlName": "Cyber Risk Management",
      "mappingStrength": "Partial",
      "mappingNotes": "Supply chain risk management aligns to CAF cyber risk management"
    },
    {
      "@id": "rcsg-fw:map-B1-CAF-001",
      "@type": "rcsg-fw:GovernanceActionMapping",
      "actionRef": "rcsg-fw:action-B1",
      "mappingId": "MAP-B1-CAF-001",
      "targetFramework": "NCSC CAF",
      "targetFrameworkVersion": "4.0",
      "targetControlId": "A1",
      "targetControlName": "Governance",
      "mappingStrength": "Full",
      "mappingNotes": "Cyber strategy development maps to CAF governance principle"
    },
    {
      "@id": "rcsg-fw:map-B2-CAF-001",
      "@type": "rcsg-fw:GovernanceActionMapping",
      "actionRef": "rcsg-fw:action-B2",
      "mappingId": "MAP-B2-CAF-001",
      "targetFramework": "NCSC CAF",
      "targetFrameworkVersion": "4.0",
      "targetControlId": "A1",
      "targetControlName": "Governance",
      "mappingStrength": "Full",
      "mappingNotes": "Strategy resourcing maps to CAF governance principle"
    },
    {
      "@id": "rcsg-fw:map-C1-CAF-001",
      "@type": "rcsg-fw:GovernanceActionMapping",
      "actionRef": "rcsg-fw:action-C1",
      "mappingId": "MAP-C1-CAF-001",
      "targetFramework": "NCSC CAF",
      "targetFrameworkVersion": "4.0",
      "targetControlId": "B6",
      "targetControlName": "Staff awareness and training",
      "mappingStrength": "Full",
      "mappingNotes": "Security culture promotion maps to CAF staff awareness and training"
    },
    {
      "@id": "rcsg-fw:map-C2-CAF-001",
      "@type": "rcsg-fw:GovernanceActionMapping",
      "actionRef": "rcsg-fw:action-C2",
      "mappingId": "MAP-C2-CAF-001",
      "targetFramework": "NCSC CAF",
      "targetFrameworkVersion": "4.0",
      "targetControlId": "A1",
      "targetControlName": "Governance",
      "mappingStrength": "Partial",
      "mappingNotes": "Skills development aligns to CAF governance and service protection"
    },
    {
      "@id": "rcsg-fw:map-C2-CAF-002",
      "@type": "rcsg-fw:GovernanceActionMapping",
      "actionRef": "rcsg-fw:action-C2",
      "mappingId": "MAP-C2-CAF-002",
      "targetFramework": "NCSC CAF",
      "targetFrameworkVersion": "4.0",
      "targetControlId": "B1",
      "targetControlName": "Service Protection Policies, Processes and Procedures",
      "mappingStrength": "Partial",
      "mappingNotes": "Skills development also aligns to CAF service protection policies"
    },
    {
      "@id": "rcsg-fw:map-C3-CAF-001",
      "@type": "rcsg-fw:GovernanceActionMapping",
      "actionRef": "rcsg-fw:action-C3",
      "mappingId": "MAP-C3-CAF-001",
      "targetFramework": "NCSC CAF",
      "targetFrameworkVersion": "4.0",
      "targetControlId": "B6",
      "targetControlName": "Staff awareness and training",
      "mappingStrength": "Full",
      "mappingNotes": "Role embedding maps to CAF staff awareness and training"
    },
    {
      "@id": "rcsg-fw:map-C4-CAF-001",
      "@type": "rcsg-fw:GovernanceActionMapping",
      "actionRef": "rcsg-fw:action-C4",
      "mappingId": "MAP-C4-CAF-001",
      "targetFramework": "NCSC CAF",
      "targetFrameworkVersion": "4.0",
      "targetControlId": "B6",
      "targetControlName": "Staff awareness and training",
      "mappingStrength": "Partial",
      "mappingNotes": "Board cyber literacy aligns to CAF staff awareness at leadership level"
    },
    {
      "@id": "rcsg-fw:map-D1-CAF-001",
      "@type": "rcsg-fw:GovernanceActionMapping",
      "actionRef": "rcsg-fw:action-D1",
      "mappingId": "MAP-D1-CAF-001",
      "targetFramework": "NCSC CAF",
      "targetFrameworkVersion": "4.0",
      "targetControlId": "D1",
      "targetControlName": "Response and Recovery Planning",
      "mappingStrength": "Full",
      "mappingNotes": "Incident response planning maps directly to CAF response and recovery"
    },
    {
      "@id": "rcsg-fw:map-D2-CAF-001",
      "@type": "rcsg-fw:GovernanceActionMapping",
      "actionRef": "rcsg-fw:action-D2",
      "mappingId": "MAP-D2-CAF-001",
      "targetFramework": "NCSC CAF",
      "targetFrameworkVersion": "4.0",
      "targetControlId": "D1",
      "targetControlName": "Response and Recovery Planning",
      "mappingStrength": "Full",
      "mappingNotes": "Testing and exercising plans maps to CAF response and recovery"
    },
    {
      "@id": "rcsg-fw:map-D3-CAF-001",
      "@type": "rcsg-fw:GovernanceActionMapping",
      "actionRef": "rcsg-fw:action-D3",
      "mappingId": "MAP-D3-CAF-001",
      "targetFramework": "NCSC CAF",
      "targetFrameworkVersion": "4.0",
      "targetControlId": "D1",
      "targetControlName": "Response and Recovery Planning",
      "mappingStrength": "Full",
      "mappingNotes": "Communication protocols map to CAF response and recovery planning"
    },
    {
      "@id": "rcsg-fw:map-D4-CAF-001",
      "@type": "rcsg-fw:GovernanceActionMapping",
      "actionRef": "rcsg-fw:action-D4",
      "mappingId": "MAP-D4-CAF-001",
      "targetFramework": "NCSC CAF",
      "targetFrameworkVersion": "4.0",
      "targetControlId": "D1",
      "targetControlName": "Response and Recovery Planning",
      "mappingStrength": "Full",
      "mappingNotes": "Learning from incidents maps to CAF response and recovery"
    },
    {
      "@id": "rcsg-fw:map-E1-CAF-001",
      "@type": "rcsg-fw:GovernanceActionMapping",
      "actionRef": "rcsg-fw:action-E1",
      "mappingId": "MAP-E1-CAF-001",
      "targetFramework": "NCSC CAF",
      "targetFrameworkVersion": "4.0",
      "targetControlId": "A1",
      "targetControlName": "Governance",
      "mappingStrength": "Full",
      "mappingNotes": "Governance structure establishment maps directly to CAF governance"
    },
    {
      "@id": "rcsg-fw:map-E2-CAF-001",
      "@type": "rcsg-fw:GovernanceActionMapping",
      "actionRef": "rcsg-fw:action-E2",
      "mappingId": "MAP-E2-CAF-001",
      "targetFramework": "NCSC CAF",
      "targetFrameworkVersion": "4.0",
      "targetControlId": "A2",
      "targetControlName": "Risk Management",
      "mappingStrength": "Full",
      "mappingNotes": "Assurance on resilience maps to CAF risk management"
    },
    {
      "@id": "rcsg-fw:map-E3-CAF-001",
      "@type": "rcsg-fw:GovernanceActionMapping",
      "actionRef": "rcsg-fw:action-E3",
      "mappingId": "MAP-E3-CAF-001",
      "targetFramework": "NCSC CAF",
      "targetFrameworkVersion": "4.0",
      "targetControlId": "A2",
      "targetControlName": "Risk Management",
      "mappingStrength": "Full",
      "mappingNotes": "Review and adapt approach maps to CAF risk management"
    },
    {
      "@id": "rcsg-fw:map-E4-CAF-001",
      "@type": "rcsg-fw:GovernanceActionMapping",
      "actionRef": "rcsg-fw:action-E4",
      "mappingId": "MAP-E4-CAF-001",
      "targetFramework": "NCSC CAF",
      "targetFrameworkVersion": "4.0",
      "targetControlId": "A2.b",
      "targetControlName": "Assurance",
      "mappingStrength": "Full",
      "mappingNotes": "Governance reporting maps to CAF assurance sub-principle"
    },
    {
      "@id": "rcsg-fw:map-A1-COBIT-001",
      "@type": "rcsg-fw:GovernanceActionMapping",
      "actionRef": "rcsg-fw:action-A1",
      "mappingId": "MAP-A1-COBIT-001",
      "targetFramework": "ISACA COBIT 2019",
      "targetFrameworkVersion": "2019",
      "targetControlId": "BAI09.02, DSS04.01",
      "targetControlName": "Manage critical assets; Define BCP scope",
      "mappingStrength": "Partial",
      "mappingNotes": "Risk appetite determination aligns to COBIT asset management and BCP objectives"
    },
    {
      "@id": "rcsg-fw:map-A2-COBIT-001",
      "@type": "rcsg-fw:GovernanceActionMapping",
      "actionRef": "rcsg-fw:action-A2",
      "mappingId": "MAP-A2-COBIT-001",
      "targetFramework": "ISACA COBIT 2019",
      "targetFrameworkVersion": "2019",
      "targetControlId": "EDM01, APO01.05",
      "targetControlName": "Governance Framework; Roles and Responsibilities",
      "mappingStrength": "Full",
      "mappingNotes": "Asset identification maps to COBIT governance framework and role establishment"
    },
    {
      "@id": "rcsg-fw:map-A3-COBIT-001",
      "@type": "rcsg-fw:GovernanceActionMapping",
      "actionRef": "rcsg-fw:action-A3",
      "mappingId": "MAP-A3-COBIT-001",
      "targetFramework": "ISACA COBIT 2019",
      "targetFrameworkVersion": "2019",
      "targetControlId": "EDM03.01, APO12.02, APO13.02, BAI02.03",
      "targetControlName": "Evaluate risk; Analyse risk; Risk treatment; Requirements risk",
      "mappingStrength": "Full",
      "mappingNotes": "Risk assessment maps across multiple COBIT risk management processes"
    },
    {
      "@id": "rcsg-fw:map-A4-COBIT-001",
      "@type": "rcsg-fw:GovernanceActionMapping",
      "actionRef": "rcsg-fw:action-A4",
      "mappingId": "MAP-A4-COBIT-001",
      "targetFramework": "ISACA COBIT 2019",
      "targetFrameworkVersion": "2019",
      "targetControlId": "APO10.05",
      "targetControlName": "Monitor vendor performance and compliance",
      "mappingStrength": "Partial",
      "mappingNotes": "Threat landscape maps to COBIT vendor monitoring"
    },
    {
      "@id": "rcsg-fw:map-A5-COBIT-001",
      "@type": "rcsg-fw:GovernanceActionMapping",
      "actionRef": "rcsg-fw:action-A5",
      "mappingId": "MAP-A5-COBIT-001",
      "targetFramework": "ISACA COBIT 2019",
      "targetFrameworkVersion": "2019",
      "targetControlId": "APO01.11, MEA04.08, MEA04.09",
      "targetControlName": "Continual improvement; Assurance reporting; Follow-up actions",
      "mappingStrength": "Partial",
      "mappingNotes": "Supply chain risk maps to COBIT continual improvement and assurance follow-up"
    },
    {
      "@id": "rcsg-fw:map-B1-COBIT-001",
      "@type": "rcsg-fw:GovernanceActionMapping",
      "actionRef": "rcsg-fw:action-B1",
      "mappingId": "MAP-B1-COBIT-001",
      "targetFramework": "ISACA COBIT 2019",
      "targetFrameworkVersion": "2019",
      "targetControlId": "APO02.05, APO02.06",
      "targetControlName": "Strategic plan and road map; Communicate strategy",
      "mappingStrength": "Full",
      "mappingNotes": "Cyber strategy development maps to COBIT strategic planning and communication"
    },
    {
      "@id": "rcsg-fw:map-B2-COBIT-001",
      "@type": "rcsg-fw:GovernanceActionMapping",
      "actionRef": "rcsg-fw:action-B2",
      "mappingId": "MAP-B2-COBIT-001",
      "targetFramework": "ISACA COBIT 2019",
      "targetFrameworkVersion": "2019",
      "targetControlId": "EDM03.01, EDM03.02, APO12.02, APO12.03, MEA03",
      "targetControlName": "Evaluate and direct risk; Analyse risk; Risk profile; Compliance",
      "mappingStrength": "Full",
      "mappingNotes": "Strategy resourcing maps to COBIT risk evaluation, profiling, and compliance"
    },
    {
      "@id": "rcsg-fw:map-B3-COBIT-001",
      "@type": "rcsg-fw:GovernanceActionMapping",
      "actionRef": "rcsg-fw:action-B3",
      "mappingId": "MAP-B3-COBIT-001",
      "targetFramework": "ISACA COBIT 2019",
      "targetFrameworkVersion": "2019",
      "targetControlId": "APO06.02, EDM04.02",
      "targetControlName": "Prioritise resource allocation; Direct resource management",
      "mappingStrength": "Partial",
      "mappingNotes": "Policy and process maps to COBIT resource prioritisation"
    },
    {
      "@id": "rcsg-fw:map-B4-COBIT-001",
      "@type": "rcsg-fw:GovernanceActionMapping",
      "actionRef": "rcsg-fw:action-B4",
      "mappingId": "MAP-B4-COBIT-001",
      "targetFramework": "ISACA COBIT 2019",
      "targetFrameworkVersion": "2019",
      "targetControlId": "EDM02.04",
      "targetControlName": "Monitor value optimisation",
      "mappingStrength": "Partial",
      "mappingNotes": "Technical controls effectiveness maps to COBIT value optimisation monitoring"
    },
    {
      "@id": "rcsg-fw:map-C1-COBIT-001",
      "@type": "rcsg-fw:GovernanceActionMapping",
      "actionRef": "rcsg-fw:action-C1",
      "mappingId": "MAP-C1-COBIT-001",
      "targetFramework": "ISACA COBIT 2019",
      "targetFrameworkVersion": "2019",
      "targetControlId": "APO01.01, APO01.02",
      "targetControlName": "Design management system; Communicate objectives",
      "mappingStrength": "Full",
      "mappingNotes": "Security culture maps to COBIT management system design and objective communication"
    },
    {
      "@id": "rcsg-fw:map-C4-COBIT-001",
      "@type": "rcsg-fw:GovernanceActionMapping",
      "actionRef": "rcsg-fw:action-C4",
      "mappingId": "MAP-C4-COBIT-001",
      "targetFramework": "ISACA COBIT 2019",
      "targetFrameworkVersion": "2019",
      "targetControlId": "APO07.03, DSS04.06",
      "targetControlName": "Maintain skills; Continuity plan training",
      "mappingStrength": "Partial",
      "mappingNotes": "Board cyber literacy maps to COBIT skills maintenance and training"
    },
    {
      "@id": "rcsg-fw:map-D2-COBIT-001",
      "@type": "rcsg-fw:GovernanceActionMapping",
      "actionRef": "rcsg-fw:action-D2",
      "mappingId": "MAP-D2-COBIT-001",
      "targetFramework": "ISACA COBIT 2019",
      "targetFrameworkVersion": "2019",
      "targetControlId": "DSS04.04",
      "targetControlName": "Exercise, test and review BCP and DRP",
      "mappingStrength": "Full",
      "mappingNotes": "Testing incident plans maps directly to COBIT BCP/DRP testing"
    },
    {
      "@id": "rcsg-fw:map-D3-COBIT-001",
      "@type": "rcsg-fw:GovernanceActionMapping",
      "actionRef": "rcsg-fw:action-D3",
      "mappingId": "MAP-D3-COBIT-001",
      "targetFramework": "ISACA COBIT 2019",
      "targetFrameworkVersion": "2019",
      "targetControlId": "DSS02",
      "targetControlName": "Managed Service Requests and Incidents",
      "mappingStrength": "Full",
      "mappingNotes": "Communication protocols map to COBIT incident management process"
    },
    {
      "@id": "rcsg-fw:map-D4-COBIT-001",
      "@type": "rcsg-fw:GovernanceActionMapping",
      "actionRef": "rcsg-fw:action-D4",
      "mappingId": "MAP-D4-COBIT-001",
      "targetFramework": "ISACA COBIT 2019",
      "targetFrameworkVersion": "2019",
      "targetControlId": "DSS04.08",
      "targetControlName": "Post-resumption review",
      "mappingStrength": "Full",
      "mappingNotes": "Learning from incidents maps to COBIT post-resumption review"
    },
    {
      "@id": "rcsg-fw:map-E1-COBIT-001",
      "@type": "rcsg-fw:GovernanceActionMapping",
      "actionRef": "rcsg-fw:action-E1",
      "mappingId": "MAP-E1-COBIT-001",
      "targetFramework": "ISACA COBIT 2019",
      "targetFrameworkVersion": "2019",
      "targetControlId": "EDM01.02, APO01.04",
      "targetControlName": "Direct governance system; Organisational structures",
      "mappingStrength": "Full",
      "mappingNotes": "Governance structure maps to COBIT governance system direction"
    },
    {
      "@id": "rcsg-fw:map-E2-COBIT-001",
      "@type": "rcsg-fw:GovernanceActionMapping",
      "actionRef": "rcsg-fw:action-E2",
      "mappingId": "MAP-E2-COBIT-001",
      "targetFramework": "ISACA COBIT 2019",
      "targetFrameworkVersion": "2019",
      "targetControlId": "MEA01",
      "targetControlName": "Managed Performance and Conformance Monitoring",
      "mappingStrength": "Full",
      "mappingNotes": "Assurance on resilience maps to COBIT performance monitoring"
    },
    {
      "@id": "rcsg-fw:map-E3-COBIT-001",
      "@type": "rcsg-fw:GovernanceActionMapping",
      "actionRef": "rcsg-fw:action-E3",
      "mappingId": "MAP-E3-COBIT-001",
      "targetFramework": "ISACA COBIT 2019",
      "targetFrameworkVersion": "2019",
      "targetControlId": "EDM05",
      "targetControlName": "Ensured Stakeholder Engagement",
      "mappingStrength": "Partial",
      "mappingNotes": "Review and adapt maps to COBIT stakeholder engagement"
    },
    {
      "@id": "rcsg-fw:map-E4-COBIT-001",
      "@type": "rcsg-fw:GovernanceActionMapping",
      "actionRef": "rcsg-fw:action-E4",
      "mappingId": "MAP-E4-COBIT-001",
      "targetFramework": "ISACA COBIT 2019",
      "targetFrameworkVersion": "2019",
      "targetControlId": "MEA04",
      "targetControlName": "Managed Assurance",
      "mappingStrength": "Full",
      "mappingNotes": "Governance reporting maps to COBIT managed assurance"
    },
    {
      "@id": "rcsg-fw:map-E5-COBIT-001",
      "@type": "rcsg-fw:GovernanceActionMapping",
      "actionRef": "rcsg-fw:action-E5",
      "mappingId": "MAP-E5-COBIT-001",
      "targetFramework": "ISACA COBIT 2019",
      "targetFrameworkVersion": "2019",
      "targetControlId": "MEA03",
      "targetControlName": "Managed Compliance with External Requirements",
      "mappingStrength": "Full",
      "mappingNotes": "Regulatory compliance maps to COBIT external requirements compliance"
    },
    {
      "@id": "rcsg-fw:map-A1-NIST-001",
      "@type": "rcsg-fw:GovernanceActionMapping",
      "actionRef": "rcsg-fw:action-A1",
      "mappingId": "MAP-A1-NIST-001",
      "targetFramework": "NIST CSF",
      "targetFrameworkVersion": "2.0",
      "targetControlId": "GV.OC-02, GV.OC-03, GV.OC-04, GV.RM-01, ID.AM-05",
      "targetControlName": "Organisational context; Risk management strategy; Asset identification",
      "mappingStrength": "Full",
      "mappingNotes": "Risk appetite maps to multiple NIST CSF governance and identify functions"
    },
    {
      "@id": "rcsg-fw:map-A2-NIST-001",
      "@type": "rcsg-fw:GovernanceActionMapping",
      "actionRef": "rcsg-fw:action-A2",
      "mappingId": "MAP-A2-NIST-001",
      "targetFramework": "NIST CSF",
      "targetFrameworkVersion": "2.0",
      "targetControlId": "GV.RR.01, GV.RM.03",
      "targetControlName": "Roles and responsibilities; Risk management processes",
      "mappingStrength": "Full",
      "mappingNotes": "Asset identification maps to NIST roles, responsibilities, and risk management"
    },
    {
      "@id": "rcsg-fw:map-A3-NIST-001",
      "@type": "rcsg-fw:GovernanceActionMapping",
      "actionRef": "rcsg-fw:action-A3",
      "mappingId": "MAP-A3-NIST-001",
      "targetFramework": "NIST CSF",
      "targetFrameworkVersion": "2.0",
      "targetControlId": "GV.OC.01, GV.RM.02",
      "targetControlName": "Organisational context; Risk management decisions",
      "mappingStrength": "Full",
      "mappingNotes": "Risk assessment maps to NIST organisational context and risk decisions"
    },
    {
      "@id": "rcsg-fw:map-A4-NIST-001",
      "@type": "rcsg-fw:GovernanceActionMapping",
      "actionRef": "rcsg-fw:action-A4",
      "mappingId": "MAP-A4-NIST-001",
      "targetFramework": "NIST CSF",
      "targetFrameworkVersion": "2.0",
      "targetControlId": "GV.SC.01-10, ID.RA.10",
      "targetControlName": "Supply chain risk management; Risk assessment",
      "mappingStrength": "Full",
      "mappingNotes": "Threat landscape maps to NIST supply chain risk management and risk assessment"
    },
    {
      "@id": "rcsg-fw:map-A5-NIST-001",
      "@type": "rcsg-fw:GovernanceActionMapping",
      "actionRef": "rcsg-fw:action-A5",
      "mappingId": "MAP-A5-NIST-001",
      "targetFramework": "NIST CSF",
      "targetFrameworkVersion": "2.0",
      "targetControlId": "ID.RA.01-09",
      "targetControlName": "Risk assessment categories",
      "mappingStrength": "Full",
      "mappingNotes": "Supply chain risk maps to NIST risk assessment categories"
    },
    {
      "@id": "rcsg-fw:map-B1-NIST-001",
      "@type": "rcsg-fw:GovernanceActionMapping",
      "actionRef": "rcsg-fw:action-B1",
      "mappingId": "MAP-B1-NIST-001",
      "targetFramework": "NIST CSF",
      "targetFrameworkVersion": "2.0",
      "targetControlId": "GV.RM.04",
      "targetControlName": "Risk management priorities",
      "mappingStrength": "Partial",
      "mappingNotes": "Strategy development aligns to NIST risk management priorities"
    },
    {
      "@id": "rcsg-fw:map-B2-NIST-001",
      "@type": "rcsg-fw:GovernanceActionMapping",
      "actionRef": "rcsg-fw:action-B2",
      "mappingId": "MAP-B2-NIST-001",
      "targetFramework": "NIST CSF",
      "targetFrameworkVersion": "2.0",
      "targetControlId": "GV.RM.04",
      "targetControlName": "Risk management priorities",
      "mappingStrength": "Partial",
      "mappingNotes": "Strategy resourcing aligns to NIST risk management priorities"
    },
    {
      "@id": "rcsg-fw:map-B3-NIST-001",
      "@type": "rcsg-fw:GovernanceActionMapping",
      "actionRef": "rcsg-fw:action-B3",
      "mappingId": "MAP-B3-NIST-001",
      "targetFramework": "NIST CSF",
      "targetFrameworkVersion": "2.0",
      "targetControlId": "GV-RR.03",
      "targetControlName": "Roles and responsibilities management",
      "mappingStrength": "Partial",
      "mappingNotes": "Policies and processes map to NIST roles and responsibilities"
    },
    {
      "@id": "rcsg-fw:map-B4-NIST-001",
      "@type": "rcsg-fw:GovernanceActionMapping",
      "actionRef": "rcsg-fw:action-B4",
      "mappingId": "MAP-B4-NIST-001",
      "targetFramework": "NIST CSF",
      "targetFrameworkVersion": "2.0",
      "targetControlId": "GV.RR.02",
      "targetControlName": "Roles and responsibilities oversight",
      "mappingStrength": "Partial",
      "mappingNotes": "Technical controls map to NIST oversight responsibilities"
    },
    {
      "@id": "rcsg-fw:map-C1-NIST-001",
      "@type": "rcsg-fw:GovernanceActionMapping",
      "actionRef": "rcsg-fw:action-C1",
      "mappingId": "MAP-C1-NIST-001",
      "targetFramework": "NIST CSF",
      "targetFrameworkVersion": "2.0",
      "targetControlId": "GV.RR.01, GV.RR.04",
      "targetControlName": "Roles and responsibilities; Workforce",
      "mappingStrength": "Full",
      "mappingNotes": "Security culture maps to NIST workforce and roles categories"
    },
    {
      "@id": "rcsg-fw:map-C2-NIST-001",
      "@type": "rcsg-fw:GovernanceActionMapping",
      "actionRef": "rcsg-fw:action-C2",
      "mappingId": "MAP-C2-NIST-001",
      "targetFramework": "NIST CSF",
      "targetFrameworkVersion": "2.0",
      "targetControlId": "GV.PO.01, GV.PO.02",
      "targetControlName": "Policy; Policy implementation",
      "mappingStrength": "Full",
      "mappingNotes": "Skills development maps to NIST policy and implementation"
    },
    {
      "@id": "rcsg-fw:map-C3-NIST-001",
      "@type": "rcsg-fw:GovernanceActionMapping",
      "actionRef": "rcsg-fw:action-C3",
      "mappingId": "MAP-C3-NIST-001",
      "targetFramework": "NIST CSF",
      "targetFrameworkVersion": "2.0",
      "targetControlId": "GV.PO.01, PR.AT.01, PR.AT.02",
      "targetControlName": "Policy; Awareness and training",
      "mappingStrength": "Full",
      "mappingNotes": "Role embedding maps to NIST policy and awareness/training"
    },
    {
      "@id": "rcsg-fw:map-C4-NIST-001",
      "@type": "rcsg-fw:GovernanceActionMapping",
      "actionRef": "rcsg-fw:action-C4",
      "mappingId": "MAP-C4-NIST-001",
      "targetFramework": "NIST CSF",
      "targetFrameworkVersion": "2.0",
      "targetControlId": "PR.AT.01, PR.AT.02",
      "targetControlName": "Awareness and training",
      "mappingStrength": "Partial",
      "mappingNotes": "Board literacy maps to NIST awareness and training at leadership level"
    },
    {
      "@id": "rcsg-fw:map-D1-NIST-001",
      "@type": "rcsg-fw:GovernanceActionMapping",
      "actionRef": "rcsg-fw:action-D1",
      "mappingId": "MAP-D1-NIST-001",
      "targetFramework": "NIST CSF",
      "targetFrameworkVersion": "2.0",
      "targetControlId": "RS.MA.01, RC.RP-01",
      "targetControlName": "Response management; Recovery planning",
      "mappingStrength": "Full",
      "mappingNotes": "Incident response planning maps to NIST response and recovery"
    },
    {
      "@id": "rcsg-fw:map-D2-NIST-001",
      "@type": "rcsg-fw:GovernanceActionMapping",
      "actionRef": "rcsg-fw:action-D2",
      "mappingId": "MAP-D2-NIST-001",
      "targetFramework": "NIST CSF",
      "targetFrameworkVersion": "2.0",
      "targetControlId": "ID.IM.02",
      "targetControlName": "Improvement",
      "mappingStrength": "Partial",
      "mappingNotes": "Plan testing maps to NIST improvement category"
    },
    {
      "@id": "rcsg-fw:map-D3-NIST-001",
      "@type": "rcsg-fw:GovernanceActionMapping",
      "actionRef": "rcsg-fw:action-D3",
      "mappingId": "MAP-D3-NIST-001",
      "targetFramework": "NIST CSF",
      "targetFrameworkVersion": "2.0",
      "targetControlId": "GV.OC.03, RS.MA.02",
      "targetControlName": "Organisational context; Response management",
      "mappingStrength": "Full",
      "mappingNotes": "Communication protocols map to NIST response management"
    },
    {
      "@id": "rcsg-fw:map-D4-NIST-001",
      "@type": "rcsg-fw:GovernanceActionMapping",
      "actionRef": "rcsg-fw:action-D4",
      "mappingId": "MAP-D4-NIST-001",
      "targetFramework": "NIST CSF",
      "targetFrameworkVersion": "2.0",
      "targetControlId": "RS.AN.03",
      "targetControlName": "Response analysis",
      "mappingStrength": "Full",
      "mappingNotes": "Learning from incidents maps to NIST response analysis"
    },
    {
      "@id": "rcsg-fw:map-E1-NIST-001",
      "@type": "rcsg-fw:GovernanceActionMapping",
      "actionRef": "rcsg-fw:action-E1",
      "mappingId": "MAP-E1-NIST-001",
      "targetFramework": "NIST CSF",
      "targetFrameworkVersion": "2.0",
      "targetControlId": "GV.RR.02, GV.PO-02, GV.OV-01, GV.OV-02, GV.OV-03",
      "targetControlName": "Roles; Policy; Oversight",
      "mappingStrength": "Full",
      "mappingNotes": "Governance structure maps to NIST roles, policy, and oversight"
    },
    {
      "@id": "rcsg-fw:map-E2-NIST-001",
      "@type": "rcsg-fw:GovernanceActionMapping",
      "actionRef": "rcsg-fw:action-E2",
      "mappingId": "MAP-E2-NIST-001",
      "targetFramework": "NIST CSF",
      "targetFrameworkVersion": "2.0",
      "targetControlId": "GV.RR.02, GV.OC-02, GV.OC-03",
      "targetControlName": "Roles; Organisational context",
      "mappingStrength": "Full",
      "mappingNotes": "Assurance maps to NIST roles and organisational context"
    },
    {
      "@id": "rcsg-fw:map-E3-NIST-001",
      "@type": "rcsg-fw:GovernanceActionMapping",
      "actionRef": "rcsg-fw:action-E3",
      "mappingId": "MAP-E3-NIST-001",
      "targetFramework": "NIST CSF",
      "targetFrameworkVersion": "2.0",
      "targetControlId": "GV.RR.01, GV.OC-02, GV.OC-03",
      "targetControlName": "Roles and responsibilities; Context",
      "mappingStrength": "Full",
      "mappingNotes": "Review and adapt maps to NIST roles and context categories"
    },
    {
      "@id": "rcsg-fw:map-E4-NIST-001",
      "@type": "rcsg-fw:GovernanceActionMapping",
      "actionRef": "rcsg-fw:action-E4",
      "mappingId": "MAP-E4-NIST-001",
      "targetFramework": "NIST CSF",
      "targetFrameworkVersion": "2.0",
      "targetControlId": "GV.OC-03",
      "targetControlName": "Organisational context",
      "mappingStrength": "Partial",
      "mappingNotes": "Governance reporting aligns to NIST organisational context"
    },
    {
      "@id": "rcsg-fw:map-E5-NIST-001",
      "@type": "rcsg-fw:GovernanceActionMapping",
      "actionRef": "rcsg-fw:action-E5",
      "mappingId": "MAP-E5-NIST-001",
      "targetFramework": "NIST CSF",
      "targetFrameworkVersion": "2.0",
      "targetControlId": "GV.OC-03",
      "targetControlName": "Organisational context",
      "mappingStrength": "Partial",
      "mappingNotes": "Regulatory compliance aligns to NIST organisational context"
    },
    {
      "@id": "rcsg-fw:map-A1-IASME-001",
      "@type": "rcsg-fw:GovernanceActionMapping",
      "actionRef": "rcsg-fw:action-A1",
      "mappingId": "MAP-A1-IASME-001",
      "targetFramework": "IASME Cyber Assurance",
      "targetFrameworkVersion": "2024",
      "targetControlId": "Theme 3, 4, 12, 13",
      "targetControlName": "Assets; Legal landscape; Secure operations; Resilience",
      "mappingStrength": "Full",
      "mappingNotes": "Risk appetite maps across IASME assets, legal, operations, and resilience themes"
    },
    {
      "@id": "rcsg-fw:map-A2-IASME-001",
      "@type": "rcsg-fw:GovernanceActionMapping",
      "actionRef": "rcsg-fw:action-A2",
      "mappingId": "MAP-A2-IASME-001",
      "targetFramework": "IASME Cyber Assurance",
      "targetFrameworkVersion": "2024",
      "targetControlId": "Theme 5",
      "targetControlName": "Assessing and treating risks",
      "mappingStrength": "Full",
      "mappingNotes": "Asset identification maps to IASME risk assessment theme"
    },
    {
      "@id": "rcsg-fw:map-A3-IASME-001",
      "@type": "rcsg-fw:GovernanceActionMapping",
      "actionRef": "rcsg-fw:action-A3",
      "mappingId": "MAP-A3-IASME-001",
      "targetFramework": "IASME Cyber Assurance",
      "targetFrameworkVersion": "2024",
      "targetControlId": "Theme 5",
      "targetControlName": "Assessing and treating risks",
      "mappingStrength": "Full",
      "mappingNotes": "Risk assessment maps directly to IASME risk theme"
    },
    {
      "@id": "rcsg-fw:map-A4-IASME-001",
      "@type": "rcsg-fw:GovernanceActionMapping",
      "actionRef": "rcsg-fw:action-A4",
      "mappingId": "MAP-A4-IASME-001",
      "targetFramework": "IASME Cyber Assurance",
      "targetFrameworkVersion": "2024",
      "targetControlId": "Theme 5",
      "targetControlName": "Assessing and treating risks",
      "mappingStrength": "Partial",
      "mappingNotes": "Threat landscape understanding aligns to IASME risk assessment"
    },
    {
      "@id": "rcsg-fw:map-A5-IASME-001",
      "@type": "rcsg-fw:GovernanceActionMapping",
      "actionRef": "rcsg-fw:action-A5",
      "mappingId": "MAP-A5-IASME-001",
      "targetFramework": "IASME Cyber Assurance",
      "targetFrameworkVersion": "2024",
      "targetControlId": "Theme 5",
      "targetControlName": "Assessing and treating risks",
      "mappingStrength": "Partial",
      "mappingNotes": "Supply chain risk maps to IASME risk assessment"
    },
    {
      "@id": "rcsg-fw:map-B1-IASME-001",
      "@type": "rcsg-fw:GovernanceActionMapping",
      "actionRef": "rcsg-fw:action-B1",
      "mappingId": "MAP-B1-IASME-001",
      "targetFramework": "IASME Cyber Assurance",
      "targetFrameworkVersion": "2024",
      "targetControlId": "Theme 1",
      "targetControlName": "Planning information security",
      "mappingStrength": "Full",
      "mappingNotes": "Cyber strategy maps to IASME information security planning"
    },
    {
      "@id": "rcsg-fw:map-B2-IASME-001",
      "@type": "rcsg-fw:GovernanceActionMapping",
      "actionRef": "rcsg-fw:action-B2",
      "mappingId": "MAP-B2-IASME-001",
      "targetFramework": "IASME Cyber Assurance",
      "targetFrameworkVersion": "2024",
      "targetControlId": "Theme 1, 5",
      "targetControlName": "Planning; Risk assessment",
      "mappingStrength": "Full",
      "mappingNotes": "Strategy resourcing maps to IASME planning and risk themes"
    },
    {
      "@id": "rcsg-fw:map-B3-IASME-001",
      "@type": "rcsg-fw:GovernanceActionMapping",
      "actionRef": "rcsg-fw:action-B3",
      "mappingId": "MAP-B3-IASME-001",
      "targetFramework": "IASME Cyber Assurance",
      "targetFrameworkVersion": "2024",
      "targetControlId": "Theme 1, 2, 7",
      "targetControlName": "Planning; Organisation; People",
      "mappingStrength": "Full",
      "mappingNotes": "Policies and processes map to IASME planning, organisation, and people themes"
    },
    {
      "@id": "rcsg-fw:map-B4-IASME-001",
      "@type": "rcsg-fw:GovernanceActionMapping",
      "actionRef": "rcsg-fw:action-B4",
      "mappingId": "MAP-B4-IASME-001",
      "targetFramework": "IASME Cyber Assurance",
      "targetFrameworkVersion": "2024",
      "targetControlId": "Theme 2, 5, 8, 12",
      "targetControlName": "Organisation; Risk; Policy realisation; Secure operations",
      "mappingStrength": "Full",
      "mappingNotes": "Technical controls map across IASME organisation, risk, policy, and operations"
    },
    {
      "@id": "rcsg-fw:map-C1-IASME-001",
      "@type": "rcsg-fw:GovernanceActionMapping",
      "actionRef": "rcsg-fw:action-C1",
      "mappingId": "MAP-C1-IASME-001",
      "targetFramework": "IASME Cyber Assurance",
      "targetFrameworkVersion": "2024",
      "targetControlId": "Theme 7, 12",
      "targetControlName": "People; Secure operations",
      "mappingStrength": "Full",
      "mappingNotes": "Security culture maps to IASME people and operations themes"
    },
    {
      "@id": "rcsg-fw:map-C2-IASME-001",
      "@type": "rcsg-fw:GovernanceActionMapping",
      "actionRef": "rcsg-fw:action-C2",
      "mappingId": "MAP-C2-IASME-001",
      "targetFramework": "IASME Cyber Assurance",
      "targetFrameworkVersion": "2024",
      "targetControlId": "Theme 8",
      "targetControlName": "Policy realisation",
      "mappingStrength": "Partial",
      "mappingNotes": "Skills development aligns to IASME policy realisation"
    },
    {
      "@id": "rcsg-fw:map-C3-IASME-001",
      "@type": "rcsg-fw:GovernanceActionMapping",
      "actionRef": "rcsg-fw:action-C3",
      "mappingId": "MAP-C3-IASME-001",
      "targetFramework": "IASME Cyber Assurance",
      "targetFrameworkVersion": "2024",
      "targetControlId": "Theme 2, 3, 7",
      "targetControlName": "Organisation; Assets; People",
      "mappingStrength": "Full",
      "mappingNotes": "Role embedding maps to IASME organisation, assets, and people themes"
    },
    {
      "@id": "rcsg-fw:map-C4-IASME-001",
      "@type": "rcsg-fw:GovernanceActionMapping",
      "actionRef": "rcsg-fw:action-C4",
      "mappingId": "MAP-C4-IASME-001",
      "targetFramework": "IASME Cyber Assurance",
      "targetFrameworkVersion": "2024",
      "targetControlId": "Theme 2, 7",
      "targetControlName": "Organisation; People",
      "mappingStrength": "Partial",
      "mappingNotes": "Board literacy maps to IASME organisation and people themes"
    },
    {
      "@id": "rcsg-fw:map-D1-IASME-001",
      "@type": "rcsg-fw:GovernanceActionMapping",
      "actionRef": "rcsg-fw:action-D1",
      "mappingId": "MAP-D1-IASME-001",
      "targetFramework": "IASME Cyber Assurance",
      "targetFrameworkVersion": "2024",
      "targetControlId": "Theme 13",
      "targetControlName": "Resilience: business continuity, incident management, and disaster recovery",
      "mappingStrength": "Full",
      "mappingNotes": "Incident response planning maps to IASME resilience theme"
    },
    {
      "@id": "rcsg-fw:map-D2-IASME-001",
      "@type": "rcsg-fw:GovernanceActionMapping",
      "actionRef": "rcsg-fw:action-D2",
      "mappingId": "MAP-D2-IASME-001",
      "targetFramework": "IASME Cyber Assurance",
      "targetFrameworkVersion": "2024",
      "targetControlId": "Theme 13",
      "targetControlName": "Resilience: business continuity, incident management, and disaster recovery",
      "mappingStrength": "Full",
      "mappingNotes": "Plan testing maps to IASME resilience theme"
    },
    {
      "@id": "rcsg-fw:map-D3-IASME-001",
      "@type": "rcsg-fw:GovernanceActionMapping",
      "actionRef": "rcsg-fw:action-D3",
      "mappingId": "MAP-D3-IASME-001",
      "targetFramework": "IASME Cyber Assurance",
      "targetFrameworkVersion": "2024",
      "targetControlId": "Theme 13",
      "targetControlName": "Resilience: business continuity, incident management, and disaster recovery",
      "mappingStrength": "Full",
      "mappingNotes": "Communication protocols map to IASME resilience theme"
    },
    {
      "@id": "rcsg-fw:map-D4-IASME-001",
      "@type": "rcsg-fw:GovernanceActionMapping",
      "actionRef": "rcsg-fw:action-D4",
      "mappingId": "MAP-D4-IASME-001",
      "targetFramework": "IASME Cyber Assurance",
      "targetFrameworkVersion": "2024",
      "targetControlId": "Theme 13",
      "targetControlName": "Resilience: business continuity, incident management, and disaster recovery",
      "mappingStrength": "Full",
      "mappingNotes": "Learning from incidents maps to IASME resilience theme"
    },
    {
      "@id": "rcsg-fw:map-E1-IASME-001",
      "@type": "rcsg-fw:GovernanceActionMapping",
      "actionRef": "rcsg-fw:action-E1",
      "mappingId": "MAP-E1-IASME-001",
      "targetFramework": "IASME Cyber Assurance",
      "targetFrameworkVersion": "2024",
      "targetControlId": "Theme 2",
      "targetControlName": "Organisation",
      "mappingStrength": "Full",
      "mappingNotes": "Governance structure maps to IASME organisation theme"
    },
    {
      "@id": "rcsg-fw:map-E2-IASME-001",
      "@type": "rcsg-fw:GovernanceActionMapping",
      "actionRef": "rcsg-fw:action-E2",
      "mappingId": "MAP-E2-IASME-001",
      "targetFramework": "IASME Cyber Assurance",
      "targetFrameworkVersion": "2024",
      "targetControlId": "Theme 12",
      "targetControlName": "Secure business operations: monitoring, review, and change management",
      "mappingStrength": "Full",
      "mappingNotes": "Assurance maps to IASME secure operations monitoring"
    },
    {
      "@id": "rcsg-fw:map-E3-IASME-001",
      "@type": "rcsg-fw:GovernanceActionMapping",
      "actionRef": "rcsg-fw:action-E3",
      "mappingId": "MAP-E3-IASME-001",
      "targetFramework": "IASME Cyber Assurance",
      "targetFrameworkVersion": "2024",
      "targetControlId": "Theme 2",
      "targetControlName": "Organisation",
      "mappingStrength": "Partial",
      "mappingNotes": "Review and adapt maps to IASME organisation theme"
    },
    {
      "@id": "rcsg-fw:map-E4-IASME-001",
      "@type": "rcsg-fw:GovernanceActionMapping",
      "actionRef": "rcsg-fw:action-E4",
      "mappingId": "MAP-E4-IASME-001",
      "targetFramework": "IASME Cyber Assurance",
      "targetFrameworkVersion": "2024",
      "targetControlId": "Theme 2, 4, 7, 8, 12",
      "targetControlName": "Organisation; Legal; People; Policy; Operations",
      "mappingStrength": "Full",
      "mappingNotes": "Governance reporting maps across five IASME themes"
    },
    {
      "@id": "rcsg-fw:map-E5-IASME-001",
      "@type": "rcsg-fw:GovernanceActionMapping",
      "actionRef": "rcsg-fw:action-E5",
      "mappingId": "MAP-E5-IASME-001",
      "targetFramework": "IASME Cyber Assurance",
      "targetFrameworkVersion": "2024",
      "targetControlId": "Theme 4",
      "targetControlName": "Legal and regulatory landscape",
      "mappingStrength": "Full",
      "mappingNotes": "Regulatory compliance maps to IASME legal and regulatory theme"
    },
    {
      "@id": "rcsg-fw:map-A1-ISA-001",
      "@type": "rcsg-fw:GovernanceActionMapping",
      "actionRef": "rcsg-fw:action-A1",
      "mappingId": "MAP-A1-ISA-001",
      "targetFramework": "ISA Directors Handbook",
      "targetFrameworkVersion": "2023",
      "targetControlId": "Principle 1",
      "targetControlName": "Cybersecurity as a Strategic Risk",
      "mappingStrength": "Full",
      "mappingNotes": "Risk appetite maps to ISA strategic risk principle"
    },
    {
      "@id": "rcsg-fw:map-A2-ISA-001",
      "@type": "rcsg-fw:GovernanceActionMapping",
      "actionRef": "rcsg-fw:action-A2",
      "mappingId": "MAP-A2-ISA-001",
      "targetFramework": "ISA Directors Handbook",
      "targetFrameworkVersion": "2023",
      "targetControlId": "Principle 4",
      "targetControlName": "An Enterprise Framework for Managing Cyber Risk",
      "mappingStrength": "Full",
      "mappingNotes": "Asset identification maps to ISA enterprise risk framework"
    },
    {
      "@id": "rcsg-fw:map-A3-ISA-001",
      "@type": "rcsg-fw:GovernanceActionMapping",
      "actionRef": "rcsg-fw:action-A3",
      "mappingId": "MAP-A3-ISA-001",
      "targetFramework": "ISA Directors Handbook",
      "targetFrameworkVersion": "2023",
      "targetControlId": "Principle 4",
      "targetControlName": "An Enterprise Framework for Managing Cyber Risk",
      "mappingStrength": "Full",
      "mappingNotes": "Risk assessment maps to ISA enterprise risk framework"
    },
    {
      "@id": "rcsg-fw:map-A4-ISA-001",
      "@type": "rcsg-fw:GovernanceActionMapping",
      "actionRef": "rcsg-fw:action-A4",
      "mappingId": "MAP-A4-ISA-001",
      "targetFramework": "ISA Directors Handbook",
      "targetFrameworkVersion": "2023",
      "targetControlId": "Principle 1, 6",
      "targetControlName": "Strategic Risk; Systemic Resilience",
      "mappingStrength": "Full",
      "mappingNotes": "Threat landscape maps to ISA strategic risk and systemic resilience"
    },
    {
      "@id": "rcsg-fw:map-A5-ISA-001",
      "@type": "rcsg-fw:GovernanceActionMapping",
      "actionRef": "rcsg-fw:action-A5",
      "mappingId": "MAP-A5-ISA-001",
      "targetFramework": "ISA Directors Handbook",
      "targetFrameworkVersion": "2023",
      "targetControlId": "Principle 2, 3",
      "targetControlName": "Legal and Disclosure; Board Oversight and Expertise",
      "mappingStrength": "Partial",
      "mappingNotes": "Supply chain risk maps to ISA legal implications and board oversight"
    },
    {
      "@id": "rcsg-fw:map-B1-ISA-001",
      "@type": "rcsg-fw:GovernanceActionMapping",
      "actionRef": "rcsg-fw:action-B1",
      "mappingId": "MAP-B1-ISA-001",
      "targetFramework": "ISA Directors Handbook",
      "targetFrameworkVersion": "2023",
      "targetControlId": "Principle 1",
      "targetControlName": "Cybersecurity as a Strategic Risk",
      "mappingStrength": "Full",
      "mappingNotes": "Cyber strategy maps to ISA strategic risk principle"
    },
    {
      "@id": "rcsg-fw:map-B2-ISA-001",
      "@type": "rcsg-fw:GovernanceActionMapping",
      "actionRef": "rcsg-fw:action-B2",
      "mappingId": "MAP-B2-ISA-001",
      "targetFramework": "ISA Directors Handbook",
      "targetFrameworkVersion": "2023",
      "targetControlId": "Principle 2, 3",
      "targetControlName": "Legal and Disclosure; Board Oversight and Expertise",
      "mappingStrength": "Full",
      "mappingNotes": "Strategy resourcing maps to ISA legal implications and board oversight"
    },
    {
      "@id": "rcsg-fw:map-C1-ISA-001",
      "@type": "rcsg-fw:GovernanceActionMapping",
      "actionRef": "rcsg-fw:action-C1",
      "mappingId": "MAP-C1-ISA-001",
      "targetFramework": "ISA Directors Handbook",
      "targetFrameworkVersion": "2023",
      "targetControlId": "Principle 1",
      "targetControlName": "Cybersecurity as a Strategic Risk",
      "mappingStrength": "Partial",
      "mappingNotes": "Security culture aligns to ISA strategic risk principle"
    },
    {
      "@id": "rcsg-fw:map-D1-ISA-001",
      "@type": "rcsg-fw:GovernanceActionMapping",
      "actionRef": "rcsg-fw:action-D1",
      "mappingId": "MAP-D1-ISA-001",
      "targetFramework": "ISA Directors Handbook",
      "targetFrameworkVersion": "2023",
      "targetControlId": "Principle 1, Tool E",
      "targetControlName": "Strategic Risk; Incident Response tool",
      "mappingStrength": "Full",
      "mappingNotes": "Incident response maps to ISA strategic risk and incident response tool"
    },
    {
      "@id": "rcsg-fw:map-E1-ISA-001",
      "@type": "rcsg-fw:GovernanceActionMapping",
      "actionRef": "rcsg-fw:action-E1",
      "mappingId": "MAP-E1-ISA-001",
      "targetFramework": "ISA Directors Handbook",
      "targetFrameworkVersion": "2023",
      "targetControlId": "Principle 4",
      "targetControlName": "An Enterprise Framework for Managing Cyber Risk",
      "mappingStrength": "Full",
      "mappingNotes": "Governance structure maps to ISA enterprise risk framework"
    },
    {
      "@id": "rcsg-fw:map-E2-ISA-001",
      "@type": "rcsg-fw:GovernanceActionMapping",
      "actionRef": "rcsg-fw:action-E2",
      "mappingId": "MAP-E2-ISA-001",
      "targetFramework": "ISA Directors Handbook",
      "targetFrameworkVersion": "2023",
      "targetControlId": "Principle 5",
      "targetControlName": "Cybersecurity Measurement and Reporting",
      "mappingStrength": "Full",
      "mappingNotes": "Assurance maps to ISA measurement and reporting principle"
    },
    {
      "@id": "rcsg-fw:map-E4-ISA-001",
      "@type": "rcsg-fw:GovernanceActionMapping",
      "actionRef": "rcsg-fw:action-E4",
      "mappingId": "MAP-E4-ISA-001",
      "targetFramework": "ISA Directors Handbook",
      "targetFrameworkVersion": "2023",
      "targetControlId": "Principle 5",
      "targetControlName": "Cybersecurity Measurement and Reporting",
      "mappingStrength": "Full",
      "mappingNotes": "Governance reporting maps to ISA measurement and reporting"
    },
    {
      "@id": "rcsg-fw:map-E5-ISA-001",
      "@type": "rcsg-fw:GovernanceActionMapping",
      "actionRef": "rcsg-fw:action-E5",
      "mappingId": "MAP-E5-ISA-001",
      "targetFramework": "ISA Directors Handbook",
      "targetFrameworkVersion": "2023",
      "targetControlId": "Principle 2",
      "targetControlName": "Legal and Disclosure Implications",
      "mappingStrength": "Full",
      "mappingNotes": "Regulatory compliance maps to ISA legal and disclosure principle"
    },
    {
      "@id": "rcsg-fw:map-A1-ANSSI-001",
      "@type": "rcsg-fw:GovernanceActionMapping",
      "actionRef": "rcsg-fw:action-A1",
      "mappingId": "MAP-A1-ANSSI-001",
      "targetFramework": "ANSSI 14-Step Approach",
      "targetFrameworkVersion": "2024",
      "targetControlId": "Step 2",
      "targetControlName": "Understanding one's digital activity",
      "mappingStrength": "Full",
      "mappingNotes": "Risk appetite maps to ANSSI understanding digital activity"
    },
    {
      "@id": "rcsg-fw:map-A2-ANSSI-001",
      "@type": "rcsg-fw:GovernanceActionMapping",
      "actionRef": "rcsg-fw:action-A2",
      "mappingId": "MAP-A2-ANSSI-001",
      "targetFramework": "ANSSI 14-Step Approach",
      "targetFrameworkVersion": "2024",
      "targetControlId": "Step 1",
      "targetControlName": "Defining a governance framework for the digital risk",
      "mappingStrength": "Full",
      "mappingNotes": "Asset identification maps to ANSSI governance framework definition"
    },
    {
      "@id": "rcsg-fw:map-A3-ANSSI-001",
      "@type": "rcsg-fw:GovernanceActionMapping",
      "actionRef": "rcsg-fw:action-A3",
      "mappingId": "MAP-A3-ANSSI-001",
      "targetFramework": "ANSSI 14-Step Approach",
      "targetFrameworkVersion": "2024",
      "targetControlId": "Step 3",
      "targetControlName": "Know your risk acceptance threshold",
      "mappingStrength": "Full",
      "mappingNotes": "Risk assessment maps to ANSSI risk acceptance threshold"
    },
    {
      "@id": "rcsg-fw:map-A4-ANSSI-001",
      "@type": "rcsg-fw:GovernanceActionMapping",
      "actionRef": "rcsg-fw:action-A4",
      "mappingId": "MAP-A4-ANSSI-001",
      "targetFramework": "ANSSI 14-Step Approach",
      "targetFrameworkVersion": "2024",
      "targetControlId": "Step 3, 9",
      "targetControlName": "Risk threshold; Building protection",
      "mappingStrength": "Full",
      "mappingNotes": "Threat landscape maps to ANSSI risk threshold and protection building"
    },
    {
      "@id": "rcsg-fw:map-A5-ANSSI-001",
      "@type": "rcsg-fw:GovernanceActionMapping",
      "actionRef": "rcsg-fw:action-A5",
      "mappingId": "MAP-A5-ANSSI-001",
      "targetFramework": "ANSSI 14-Step Approach",
      "targetFrameworkVersion": "2024",
      "targetControlId": "Step 14",
      "targetControlName": "Agility: continuous improvement and performance",
      "mappingStrength": "Partial",
      "mappingNotes": "Supply chain risk aligns to ANSSI continuous improvement"
    },
    {
      "@id": "rcsg-fw:map-B1-ANSSI-001",
      "@type": "rcsg-fw:GovernanceActionMapping",
      "actionRef": "rcsg-fw:action-B1",
      "mappingId": "MAP-B1-ANSSI-001",
      "targetFramework": "ANSSI 14-Step Approach",
      "targetFrameworkVersion": "2024",
      "targetControlId": "Step 4, 5",
      "targetControlName": "Worst risk scenario; Digital security strategy",
      "mappingStrength": "Full",
      "mappingNotes": "Cyber strategy maps to ANSSI scenario planning and security strategy"
    },
    {
      "@id": "rcsg-fw:map-C1-ANSSI-001",
      "@type": "rcsg-fw:GovernanceActionMapping",
      "actionRef": "rcsg-fw:action-C1",
      "mappingId": "MAP-C1-ANSSI-001",
      "targetFramework": "ANSSI 14-Step Approach",
      "targetFrameworkVersion": "2024",
      "targetControlId": "Step 7",
      "targetControlName": "Humans at the centre of the game",
      "mappingStrength": "Full",
      "mappingNotes": "Security culture maps to ANSSI human-centred security approach"
    },
    {
      "@id": "rcsg-fw:map-D1-ANSSI-001",
      "@type": "rcsg-fw:GovernanceActionMapping",
      "actionRef": "rcsg-fw:action-D1",
      "mappingId": "MAP-D1-ANSSI-001",
      "targetFramework": "ANSSI 14-Step Approach",
      "targetFrameworkVersion": "2024",
      "targetControlId": "Step 10",
      "targetControlName": "Orienting defence and anticipating reaction",
      "mappingStrength": "Full",
      "mappingNotes": "Incident response maps to ANSSI defence orientation and anticipation"
    },
    {
      "@id": "rcsg-fw:map-D2-ANSSI-001",
      "@type": "rcsg-fw:GovernanceActionMapping",
      "actionRef": "rcsg-fw:action-D2",
      "mappingId": "MAP-D2-ANSSI-001",
      "targetFramework": "ANSSI 14-Step Approach",
      "targetFrameworkVersion": "2024",
      "targetControlId": "Step 11, 14",
      "targetControlName": "Resilience in cyberattack; Continuous improvement",
      "mappingStrength": "Full",
      "mappingNotes": "Plan testing maps to ANSSI resilience and continuous improvement"
    },
    {
      "@id": "rcsg-fw:map-E1-ANSSI-001",
      "@type": "rcsg-fw:GovernanceActionMapping",
      "actionRef": "rcsg-fw:action-E1",
      "mappingId": "MAP-E1-ANSSI-001",
      "targetFramework": "ANSSI 14-Step Approach",
      "targetFrameworkVersion": "2024",
      "targetControlId": "Step 1",
      "targetControlName": "Defining a governance framework for the digital risk",
      "mappingStrength": "Full",
      "mappingNotes": "Governance structure maps to ANSSI governance framework definition"
    },
    {
      "@id": "rcsg-fw:map-A1-ISO-001",
      "@type": "rcsg-fw:GovernanceActionMapping",
      "actionRef": "rcsg-fw:action-A1",
      "mappingId": "MAP-A1-ISO-001",
      "targetFramework": "ISO/IEC 27001:2022",
      "targetFrameworkVersion": "2022",
      "targetControlId": "Clause 4",
      "targetControlName": "Context of the organisation",
      "mappingStrength": "Full",
      "mappingNotes": "Risk appetite maps to ISO 27001 organisational context"
    },
    {
      "@id": "rcsg-fw:map-A2-ISO-001",
      "@type": "rcsg-fw:GovernanceActionMapping",
      "actionRef": "rcsg-fw:action-A2",
      "mappingId": "MAP-A2-ISO-001",
      "targetFramework": "ISO/IEC 27001:2022",
      "targetFrameworkVersion": "2022",
      "targetControlId": "Clause 5.3, Clause 6",
      "targetControlName": "Roles and responsibilities; Risk management",
      "mappingStrength": "Full",
      "mappingNotes": "Asset identification maps to ISO roles and risk management"
    },
    {
      "@id": "rcsg-fw:map-A3-ISO-001",
      "@type": "rcsg-fw:GovernanceActionMapping",
      "actionRef": "rcsg-fw:action-A3",
      "mappingId": "MAP-A3-ISO-001",
      "targetFramework": "ISO/IEC 27001:2022",
      "targetFrameworkVersion": "2022",
      "targetControlId": "Clause 6.1.2",
      "targetControlName": "Information security risk assessment",
      "mappingStrength": "Full",
      "mappingNotes": "Risk assessment maps directly to ISO risk assessment clause"
    },
    {
      "@id": "rcsg-fw:map-A5-ISO-001",
      "@type": "rcsg-fw:GovernanceActionMapping",
      "actionRef": "rcsg-fw:action-A5",
      "mappingId": "MAP-A5-ISO-001",
      "targetFramework": "ISO/IEC 27001:2022",
      "targetFrameworkVersion": "2022",
      "targetControlId": "Clause 6, 8.2, 9.1",
      "targetControlName": "Risk management; Risk assessment; Monitoring",
      "mappingStrength": "Full",
      "mappingNotes": "Supply chain risk maps to ISO risk management, assessment, and monitoring"
    },
    {
      "@id": "rcsg-fw:map-B1-ISO-001",
      "@type": "rcsg-fw:GovernanceActionMapping",
      "actionRef": "rcsg-fw:action-B1",
      "mappingId": "MAP-B1-ISO-001",
      "targetFramework": "ISO/IEC 27001:2022",
      "targetFrameworkVersion": "2022",
      "targetControlId": "Clause 5.1",
      "targetControlName": "Leadership and commitment",
      "mappingStrength": "Full",
      "mappingNotes": "Cyber strategy maps to ISO leadership and commitment"
    },
    {
      "@id": "rcsg-fw:map-B2-ISO-001",
      "@type": "rcsg-fw:GovernanceActionMapping",
      "actionRef": "rcsg-fw:action-B2",
      "mappingId": "MAP-B2-ISO-001",
      "targetFramework": "ISO/IEC 27001:2022",
      "targetFrameworkVersion": "2022",
      "targetControlId": "Clause 5.2",
      "targetControlName": "Policy",
      "mappingStrength": "Partial",
      "mappingNotes": "Strategy resourcing aligns to ISO policy establishment"
    },
    {
      "@id": "rcsg-fw:map-B3-ISO-001",
      "@type": "rcsg-fw:GovernanceActionMapping",
      "actionRef": "rcsg-fw:action-B3",
      "mappingId": "MAP-B3-ISO-001",
      "targetFramework": "ISO/IEC 27001:2022",
      "targetFrameworkVersion": "2022",
      "targetControlId": "Clause 7.1",
      "targetControlName": "Resources",
      "mappingStrength": "Full",
      "mappingNotes": "Policies and processes map to ISO resource provision"
    },
    {
      "@id": "rcsg-fw:map-B4-ISO-001",
      "@type": "rcsg-fw:GovernanceActionMapping",
      "actionRef": "rcsg-fw:action-B4",
      "mappingId": "MAP-B4-ISO-001",
      "targetFramework": "ISO/IEC 27001:2022",
      "targetFrameworkVersion": "2022",
      "targetControlId": "Clause 9.3",
      "targetControlName": "Management review",
      "mappingStrength": "Partial",
      "mappingNotes": "Technical controls effectiveness aligns to ISO management review"
    },
    {
      "@id": "rcsg-fw:map-C1-ISO-001",
      "@type": "rcsg-fw:GovernanceActionMapping",
      "actionRef": "rcsg-fw:action-C1",
      "mappingId": "MAP-C1-ISO-001",
      "targetFramework": "ISO/IEC 27001:2022",
      "targetFrameworkVersion": "2022",
      "targetControlId": "Clause 7.4",
      "targetControlName": "Communication",
      "mappingStrength": "Partial",
      "mappingNotes": "Security culture maps to ISO communication clause"
    },
    {
      "@id": "rcsg-fw:map-C2-ISO-001",
      "@type": "rcsg-fw:GovernanceActionMapping",
      "actionRef": "rcsg-fw:action-C2",
      "mappingId": "MAP-C2-ISO-001",
      "targetFramework": "ISO/IEC 27001:2022",
      "targetFrameworkVersion": "2022",
      "targetControlId": "Clause 5.1, 5.2",
      "targetControlName": "Leadership; Policy",
      "mappingStrength": "Full",
      "mappingNotes": "Skills development maps to ISO leadership and policy"
    },
    {
      "@id": "rcsg-fw:map-C3-ISO-001",
      "@type": "rcsg-fw:GovernanceActionMapping",
      "actionRef": "rcsg-fw:action-C3",
      "mappingId": "MAP-C3-ISO-001",
      "targetFramework": "ISO/IEC 27001:2022",
      "targetFrameworkVersion": "2022",
      "targetControlId": "Clause 7.2",
      "targetControlName": "Competence",
      "mappingStrength": "Full",
      "mappingNotes": "Role embedding maps to ISO competence clause"
    },
    {
      "@id": "rcsg-fw:map-C4-ISO-001",
      "@type": "rcsg-fw:GovernanceActionMapping",
      "actionRef": "rcsg-fw:action-C4",
      "mappingId": "MAP-C4-ISO-001",
      "targetFramework": "ISO/IEC 27001:2022",
      "targetFrameworkVersion": "2022",
      "targetControlId": "Clause 7.2",
      "targetControlName": "Competence",
      "mappingStrength": "Full",
      "mappingNotes": "Board cyber literacy maps to ISO competence requirements"
    },
    {
      "@id": "rcsg-fw:map-D1-ISO-001",
      "@type": "rcsg-fw:GovernanceActionMapping",
      "actionRef": "rcsg-fw:action-D1",
      "mappingId": "MAP-D1-ISO-001",
      "targetFramework": "ISO/IEC 27001:2022",
      "targetFrameworkVersion": "2022",
      "targetControlId": "Clause 6",
      "targetControlName": "Planning",
      "mappingStrength": "Full",
      "mappingNotes": "Incident response planning maps to ISO planning clause"
    },
    {
      "@id": "rcsg-fw:map-D2-ISO-001",
      "@type": "rcsg-fw:GovernanceActionMapping",
      "actionRef": "rcsg-fw:action-D2",
      "mappingId": "MAP-D2-ISO-001",
      "targetFramework": "ISO/IEC 27001:2022",
      "targetFrameworkVersion": "2022",
      "targetControlId": "Clause 9.3, 10",
      "targetControlName": "Management review; Corrective action",
      "mappingStrength": "Full",
      "mappingNotes": "Plan testing maps to ISO management review and corrective action"
    },
    {
      "@id": "rcsg-fw:map-D3-ISO-001",
      "@type": "rcsg-fw:GovernanceActionMapping",
      "actionRef": "rcsg-fw:action-D3",
      "mappingId": "MAP-D3-ISO-001",
      "targetFramework": "ISO/IEC 27001:2022",
      "targetFrameworkVersion": "2022",
      "targetControlId": "Clause 4.2",
      "targetControlName": "Understanding needs and expectations of interested parties",
      "mappingStrength": "Partial",
      "mappingNotes": "Communication protocols align to ISO stakeholder requirements"
    },
    {
      "@id": "rcsg-fw:map-D4-ISO-001",
      "@type": "rcsg-fw:GovernanceActionMapping",
      "actionRef": "rcsg-fw:action-D4",
      "mappingId": "MAP-D4-ISO-001",
      "targetFramework": "ISO/IEC 27001:2022",
      "targetFrameworkVersion": "2022",
      "targetControlId": "Clause 10",
      "targetControlName": "Nonconformity and corrective action",
      "mappingStrength": "Full",
      "mappingNotes": "Learning from incidents maps to ISO corrective action"
    },
    {
      "@id": "rcsg-fw:map-E1-ISO-001",
      "@type": "rcsg-fw:GovernanceActionMapping",
      "actionRef": "rcsg-fw:action-E1",
      "mappingId": "MAP-E1-ISO-001",
      "targetFramework": "ISO/IEC 27001:2022",
      "targetFrameworkVersion": "2022",
      "targetControlId": "Clause 5.1, 5.3",
      "targetControlName": "Leadership; Roles and responsibilities",
      "mappingStrength": "Full",
      "mappingNotes": "Governance structure maps to ISO leadership and role definitions"
    },
    {
      "@id": "rcsg-fw:map-E2-ISO-001",
      "@type": "rcsg-fw:GovernanceActionMapping",
      "actionRef": "rcsg-fw:action-E2",
      "mappingId": "MAP-E2-ISO-001",
      "targetFramework": "ISO/IEC 27001:2022",
      "targetFrameworkVersion": "2022",
      "targetControlId": "Clause 9.3",
      "targetControlName": "Management review",
      "mappingStrength": "Full",
      "mappingNotes": "Assurance maps to ISO management review"
    },
    {
      "@id": "rcsg-fw:map-E3-ISO-001",
      "@type": "rcsg-fw:GovernanceActionMapping",
      "actionRef": "rcsg-fw:action-E3",
      "mappingId": "MAP-E3-ISO-001",
      "targetFramework": "ISO/IEC 27001:2022",
      "targetFrameworkVersion": "2022",
      "targetControlId": "Clause 5.3",
      "targetControlName": "Roles, responsibilities and authorities",
      "mappingStrength": "Full",
      "mappingNotes": "Review and adapt maps to ISO role authorities"
    },
    {
      "@id": "rcsg-fw:map-E4-ISO-001",
      "@type": "rcsg-fw:GovernanceActionMapping",
      "actionRef": "rcsg-fw:action-E4",
      "mappingId": "MAP-E4-ISO-001",
      "targetFramework": "ISO/IEC 27001:2022",
      "targetFrameworkVersion": "2022",
      "targetControlId": "Clause 9.3, 9.2",
      "targetControlName": "Management review; Internal audit",
      "mappingStrength": "Full",
      "mappingNotes": "Governance reporting maps to ISO management review and internal audit"
    },
    {
      "@id": "rcsg-fw:map-E5-ISO-001",
      "@type": "rcsg-fw:GovernanceActionMapping",
      "actionRef": "rcsg-fw:action-E5",
      "mappingId": "MAP-E5-ISO-001",
      "targetFramework": "ISO/IEC 27001:2022",
      "targetFrameworkVersion": "2022",
      "targetControlId": "Clause 9.1, 4.2",
      "targetControlName": "Monitoring and measurement; Interested parties",
      "mappingStrength": "Full",
      "mappingNotes": "Regulatory compliance maps to ISO monitoring and stakeholder requirements"
    },
    {
      "@id": "rcsg-fw:map-A1-CMMI-001",
      "@type": "rcsg-fw:GovernanceActionMapping",
      "actionRef": "rcsg-fw:action-A1",
      "mappingId": "MAP-A1-CMMI-001",
      "targetFramework": "ISACA CMMI V3.0",
      "targetFrameworkVersion": "3.0",
      "targetControlId": "CONT 2.1, GOV 2.1, PCM 3.2, RSK 2.1/3.4, IRP 3.2, SDM 2.1",
      "targetControlName": "Continuity; Governance; Process Mgmt; Risk; Incident; Service Delivery",
      "mappingStrength": "Full",
      "mappingNotes": "Risk appetite maps across six CMMI practice areas"
    },
    {
      "@id": "rcsg-fw:map-A2-CMMI-001",
      "@type": "rcsg-fw:GovernanceActionMapping",
      "actionRef": "rcsg-fw:action-A2",
      "mappingId": "MAP-A2-CMMI-001",
      "targetFramework": "ISACA CMMI V3.0",
      "targetFrameworkVersion": "3.0",
      "targetControlId": "GOV 3.1, ESEC 2.4",
      "targetControlName": "Governance; Enabling Security",
      "mappingStrength": "Full",
      "mappingNotes": "Asset identification maps to CMMI governance and enabling security"
    },
    {
      "@id": "rcsg-fw:map-A3-CMMI-001",
      "@type": "rcsg-fw:GovernanceActionMapping",
      "actionRef": "rcsg-fw:action-A3",
      "mappingId": "MAP-A3-CMMI-001",
      "targetFramework": "ISACA CMMI V3.0",
      "targetFrameworkVersion": "3.0",
      "targetControlId": "ESEC 2.1, 2.4, 3.1, 3.2",
      "targetControlName": "Enabling Security practice levels",
      "mappingStrength": "Full",
      "mappingNotes": "Risk assessment maps to multiple CMMI enabling security practices"
    },
    {
      "@id": "rcsg-fw:map-A4-CMMI-001",
      "@type": "rcsg-fw:GovernanceActionMapping",
      "actionRef": "rcsg-fw:action-A4",
      "mappingId": "MAP-A4-CMMI-001",
      "targetFramework": "ISACA CMMI V3.0",
      "targetFrameworkVersion": "3.0",
      "targetControlId": "ESEC 2.3/3.3, PQA 3.1, SAM 2.2-3.2",
      "targetControlName": "Security; Quality Assurance; Supplier Agreement Mgmt",
      "mappingStrength": "Full",
      "mappingNotes": "Threat landscape maps to CMMI security, quality, and supplier management"
    },
    {
      "@id": "rcsg-fw:map-A5-CMMI-001",
      "@type": "rcsg-fw:GovernanceActionMapping",
      "actionRef": "rcsg-fw:action-A5",
      "mappingId": "MAP-A5-CMMI-001",
      "targetFramework": "ISACA CMMI V3.0",
      "targetFrameworkVersion": "3.0",
      "targetControlId": "RSK 1.1-3.5, ESEC 3.3",
      "targetControlName": "Risk and Opportunity Mgmt; Enabling Security",
      "mappingStrength": "Full",
      "mappingNotes": "Supply chain risk maps to CMMI risk management and security practices"
    },
    {
      "@id": "rcsg-fw:map-B1-CMMI-001",
      "@type": "rcsg-fw:GovernanceActionMapping",
      "actionRef": "rcsg-fw:action-B1",
      "mappingId": "MAP-B1-CMMI-001",
      "targetFramework": "ISACA CMMI V3.0",
      "targetFrameworkVersion": "3.0",
      "targetControlId": "ESEC 2.1-3.2, MST 2.1-3.1",
      "targetControlName": "Enabling Security; Managing Security Threats",
      "mappingStrength": "Full",
      "mappingNotes": "Cyber strategy maps to CMMI security and threat management practices"
    },
    {
      "@id": "rcsg-fw:map-C1-CMMI-001",
      "@type": "rcsg-fw:GovernanceActionMapping",
      "actionRef": "rcsg-fw:action-C1",
      "mappingId": "MAP-C1-CMMI-001",
      "targetFramework": "ISACA CMMI V3.0",
      "targetFrameworkVersion": "3.0",
      "targetControlId": "ESEC 2.3, 2.4",
      "targetControlName": "Enabling Security awareness practices",
      "mappingStrength": "Partial",
      "mappingNotes": "Security culture aligns to CMMI security awareness practices"
    },
    {
      "@id": "rcsg-fw:map-D1-CMMI-001",
      "@type": "rcsg-fw:GovernanceActionMapping",
      "actionRef": "rcsg-fw:action-D1",
      "mappingId": "MAP-D1-CMMI-001",
      "targetFramework": "ISACA CMMI V3.0",
      "targetFrameworkVersion": "3.0",
      "targetControlId": "CONT, IRP, ESEC, MST, RSK (entire areas)",
      "targetControlName": "Continuity; Incident; Security; Threats; Risk (all practice areas)",
      "mappingStrength": "Full",
      "mappingNotes": "Incident response maps across five CMMI practice areas"
    },
    {
      "@id": "rcsg-fw:map-E1-CMMI-001",
      "@type": "rcsg-fw:GovernanceActionMapping",
      "actionRef": "rcsg-fw:action-E1",
      "mappingId": "MAP-E1-CMMI-001",
      "targetFramework": "ISACA CMMI V3.0",
      "targetFrameworkVersion": "3.0",
      "targetControlId": "GOV (entire), ESEC 2.4/3.1/3.2",
      "targetControlName": "Governance; Enabling Security",
      "mappingStrength": "Full",
      "mappingNotes": "Governance structure maps to CMMI governance and enabling security"
    },
    {
      "@id": "rcsg-fw:map-E2-CMMI-001",
      "@type": "rcsg-fw:GovernanceActionMapping",
      "actionRef": "rcsg-fw:action-E2",
      "mappingId": "MAP-E2-CMMI-001",
      "targetFramework": "ISACA CMMI V3.0",
      "targetFrameworkVersion": "3.0",
      "targetControlId": "GOV 2.3/3.1/3.2, MPM (entire), ESEC 3.1, MC 2.1-3.3",
      "targetControlName": "Governance; Performance Measurement; Security; Monitor/Control",
      "mappingStrength": "Full",
      "mappingNotes": "Assurance maps to CMMI governance, performance, and monitoring practices"
    },
    {
      "@id": "rcsg-fw:map-A1-WEF-001",
      "@type": "rcsg-fw:GovernanceActionMapping",
      "actionRef": "rcsg-fw:action-A1",
      "mappingId": "MAP-A1-WEF-001",
      "targetFramework": "WEF Cyber Governance",
      "targetFrameworkVersion": "2024",
      "targetControlId": "2.1, 2.2, 2.3, 2.6",
      "targetControlName": "Strategic enabler; Economic drivers; Align risk mgmt; Systemic resilience",
      "mappingStrength": "Full",
      "mappingNotes": "Risk appetite maps to WEF strategic enabler, economic impact, risk alignment, and resilience"
    },
    {
      "@id": "rcsg-fw:map-A2-WEF-001",
      "@type": "rcsg-fw:GovernanceActionMapping",
      "actionRef": "rcsg-fw:action-A2",
      "mappingId": "MAP-A2-WEF-001",
      "targetFramework": "WEF Cyber Governance",
      "targetFrameworkVersion": "2024",
      "targetControlId": "2.6",
      "targetControlName": "Encourage systemic resilience and collaboration",
      "mappingStrength": "Partial",
      "mappingNotes": "Asset identification aligns to WEF systemic resilience"
    },
    {
      "@id": "rcsg-fw:map-A3-WEF-001",
      "@type": "rcsg-fw:GovernanceActionMapping",
      "actionRef": "rcsg-fw:action-A3",
      "mappingId": "MAP-A3-WEF-001",
      "targetFramework": "WEF Cyber Governance",
      "targetFrameworkVersion": "2024",
      "targetControlId": "2.4, 2.6",
      "targetControlName": "Organisational design; Systemic resilience",
      "mappingStrength": "Full",
      "mappingNotes": "Risk assessment maps to WEF organisational design and systemic resilience"
    },
    {
      "@id": "rcsg-fw:map-A4-WEF-001",
      "@type": "rcsg-fw:GovernanceActionMapping",
      "actionRef": "rcsg-fw:action-A4",
      "mappingId": "MAP-A4-WEF-001",
      "targetFramework": "WEF Cyber Governance",
      "targetFrameworkVersion": "2024",
      "targetControlId": "2.6",
      "targetControlName": "Encourage systemic resilience and collaboration",
      "mappingStrength": "Partial",
      "mappingNotes": "Threat landscape aligns to WEF systemic resilience"
    },
    {
      "@id": "rcsg-fw:map-A5-WEF-001",
      "@type": "rcsg-fw:GovernanceActionMapping",
      "actionRef": "rcsg-fw:action-A5",
      "mappingId": "MAP-A5-WEF-001",
      "targetFramework": "WEF Cyber Governance",
      "targetFrameworkVersion": "2024",
      "targetControlId": "2.2, 2.6",
      "targetControlName": "Economic drivers; Systemic resilience",
      "mappingStrength": "Full",
      "mappingNotes": "Supply chain risk maps to WEF economic impact and systemic resilience"
    },
    {
      "@id": "rcsg-fw:map-B1-WEF-001",
      "@type": "rcsg-fw:GovernanceActionMapping",
      "actionRef": "rcsg-fw:action-B1",
      "mappingId": "MAP-B1-WEF-001",
      "targetFramework": "WEF Cyber Governance",
      "targetFrameworkVersion": "2024",
      "targetControlId": "2.1, 2.3, 2.4",
      "targetControlName": "Strategic enabler; Risk alignment; Organisational design",
      "mappingStrength": "Full",
      "mappingNotes": "Cyber strategy maps to WEF strategic enabler, risk alignment, and design"
    },
    {
      "@id": "rcsg-fw:map-B2-WEF-001",
      "@type": "rcsg-fw:GovernanceActionMapping",
      "actionRef": "rcsg-fw:action-B2",
      "mappingId": "MAP-B2-WEF-001",
      "targetFramework": "WEF Cyber Governance",
      "targetFrameworkVersion": "2024",
      "targetControlId": "2.3",
      "targetControlName": "Align cyber-risk management with business needs",
      "mappingStrength": "Full",
      "mappingNotes": "Strategy resourcing maps to WEF risk-business alignment"
    },
    {
      "@id": "rcsg-fw:map-C1-WEF-001",
      "@type": "rcsg-fw:GovernanceActionMapping",
      "actionRef": "rcsg-fw:action-C1",
      "mappingId": "MAP-C1-WEF-001",
      "targetFramework": "WEF Cyber Governance",
      "targetFrameworkVersion": "2024",
      "targetControlId": "2.4",
      "targetControlName": "Ensure organizational design supports cybersecurity",
      "mappingStrength": "Full",
      "mappingNotes": "Security culture maps to WEF organisational design"
    },
    {
      "@id": "rcsg-fw:map-D2-WEF-001",
      "@type": "rcsg-fw:GovernanceActionMapping",
      "actionRef": "rcsg-fw:action-D2",
      "mappingId": "MAP-D2-WEF-001",
      "targetFramework": "WEF Cyber Governance",
      "targetFrameworkVersion": "2024",
      "targetControlId": "2.4, 2.6",
      "targetControlName": "Organisational design; Systemic resilience",
      "mappingStrength": "Partial",
      "mappingNotes": "Plan testing aligns to WEF organisational design and resilience"
    },
    {
      "@id": "rcsg-fw:map-E1-WEF-001",
      "@type": "rcsg-fw:GovernanceActionMapping",
      "actionRef": "rcsg-fw:action-E1",
      "mappingId": "MAP-E1-WEF-001",
      "targetFramework": "WEF Cyber Governance",
      "targetFrameworkVersion": "2024",
      "targetControlId": "2.5",
      "targetControlName": "Incorporate cybersecurity expertise into board governance",
      "mappingStrength": "Full",
      "mappingNotes": "Governance structure maps to WEF board expertise principle"
    },
    {
      "@id": "rcsg-fw:map-E2-WEF-001",
      "@type": "rcsg-fw:GovernanceActionMapping",
      "actionRef": "rcsg-fw:action-E2",
      "mappingId": "MAP-E2-WEF-001",
      "targetFramework": "WEF Cyber Governance",
      "targetFrameworkVersion": "2024",
      "targetControlId": "2.2",
      "targetControlName": "Understand the economic drivers and impact of cyber risk",
      "mappingStrength": "Partial",
      "mappingNotes": "Assurance aligns to WEF economic impact understanding"
    },
    {
      "@id": "rcsg-fw:map-E3-WEF-001",
      "@type": "rcsg-fw:GovernanceActionMapping",
      "actionRef": "rcsg-fw:action-E3",
      "mappingId": "MAP-E3-WEF-001",
      "targetFramework": "WEF Cyber Governance",
      "targetFrameworkVersion": "2024",
      "targetControlId": "2.6",
      "targetControlName": "Encourage systemic resilience and collaboration",
      "mappingStrength": "Partial",
      "mappingNotes": "Review and adapt aligns to WEF systemic resilience"
    },
    {
      "@id": "rcsg-fw:map-E5-WEF-001",
      "@type": "rcsg-fw:GovernanceActionMapping",
      "actionRef": "rcsg-fw:action-E5",
      "mappingId": "MAP-E5-WEF-001",
      "targetFramework": "WEF Cyber Governance",
      "targetFrameworkVersion": "2024",
      "targetControlId": "2.5",
      "targetControlName": "Incorporate cybersecurity expertise into board governance",
      "mappingStrength": "Partial",
      "mappingNotes": "Regulatory compliance aligns to WEF board expertise"
    }
  ]
}